robosoc2dgui/__init__.py
robosoc2dgui/gui.py
robosoc2dgui-1.0.0.dist-info/LICENSE
robosoc2dgui-1.0.0.dist-info/METADATA
robosoc2dgui-1.0.0.dist-info/WHEEL
robosoc2dgui-1.0.0.dist-info/top_level.txt
robosoc2dgui-1.0.0.dist-info/RECORD
