Metadata-Version: 2.1
Name: robosoc2dgui
Version: 1.0.0
Summary: GUI for robosoc2d
Home-page: https://github.com/rug
Author: Ruggero Rossi
Author-email: r.rossi@opencomplexity.com
License: UNKNOWN
Platform: UNKNOWN
Classifier: Programming Language :: Python :: 3
Classifier: License :: OSI Approved :: MIT License
Classifier: Operating System :: OS Independent
Requires-Python: >=3.6
License-File: LICENSE
Requires-Dist: robosoc2d
